{
  "tasks": [
    {
      "id": 1,
      "title": "Fazer compras"
    },
    {
      "id": 2,
      "title": "Ir ao Cinema"
    },
    {
      "id": 3,
      "title": "Estudar Matemática"
    },
    {
      "title": "",
      "id": 4
    },
    {
      "title": "",
      "id": 5
    },
    {
      "title": "",
      "id": 6
    },
    {
      "title": "",
      "id": 7
    },
    {
      "title": "",
      "id": 8
    },
    {
      "title": "Comprar pão ",
      "id": 9
    },
    {
      "title": "Lavar o Carro",
      "id": 10
    }
  ],
  "produtos": [
    {
      "id": 1,
      "nome": "Luck Tales",
      "preco": "49.99",
      "imagem": "src\\assets\\luck.jpg"
    },
    {
      "id": 2,
      "nome": "Links Awakening",
      "preco": "150.99",
      "imagem": "src\\assets\\zelda2.jpg"
    },
    {
      "id": 3,
      "nome": "Super Nintendo",
      "preco": "499",
      "imagem": ""
    }
  ]
}